<channel version="3.3.1">
  <id>aeaf7d07-c659-4cac-9378-da82754937ec</id>
  <nextMetaDataId>2</nextMetaDataId>
  <name>pureJSON</name>
  <description></description>
  <enabled>true</enabled>
  <lastModified>
    <time>1476440341908</time>
    <timezone>Africa/Blantyre</timezone>
  </lastModified>
  <revision>27</revision>
  <sourceConnector version="3.3.1">
    <metaDataId>0</metaDataId>
    <name>sourceConnector</name>
    <properties class="com.mirth.connect.connectors.http.HttpReceiverProperties" version="3.3.1">
      <pluginProperties/>
      <listenerConnectorProperties version="3.3.1">
        <host>0.0.0.0</host>
        <port>3004</port>
      </listenerConnectorProperties>
      <sourceConnectorProperties version="3.3.1">
        <responseVariable>None</responseVariable>
        <respondAfterProcessing>true</respondAfterProcessing>
        <processBatch>false</processBatch>
        <firstResponse>false</firstResponse>
        <resourceIds class="singleton-set">
          <string>Default Resource</string>
        </resourceIds>
      </sourceConnectorProperties>
      <xmlBody>false</xmlBody>
      <parseMultipart>true</parseMultipart>
      <includeMetadata>false</includeMetadata>
      <binaryMimeTypes>application/.*(?&lt;!json|xml)$|image/.*|video/.*|audio/.*</binaryMimeTypes>
      <binaryMimeTypesRegex>true</binaryMimeTypesRegex>
      <responseContentType>application/json</responseContentType>
      <responseDataTypeBinary>false</responseDataTypeBinary>
      <responseStatusCode></responseStatusCode>
      <responseHeaders class="linked-hash-map">
        <entry>
          <string>Content-Type</string>
          <list>
            <string>application/json</string>
          </list>
        </entry>
        <entry>
          <string>method</string>
          <list>
            <string>POST</string>
          </list>
        </entry>
      </responseHeaders>
      <charset>UTF-8</charset>
      <contextPath>pass_json</contextPath>
      <timeout>0</timeout>
      <staticResources/>
    </properties>
    <transformer version="3.3.1">
      <steps/>
      <inboundTemplate encoding="base64"></inboundTemplate>
      <outboundTemplate encoding="base64"></outboundTemplate>
      <inboundDataType>JSON</inboundDataType>
      <outboundDataType>JSON</outboundDataType>
      <inboundProperties class="com.mirth.connect.plugins.datatypes.json.JSONDataTypeProperties" version="3.3.1">
        <batchProperties class="com.mirth.connect.plugins.datatypes.json.JSONBatchProperties" version="3.3.1">
          <batchScript></batchScript>
        </batchProperties>
      </inboundProperties>
      <outboundProperties class="com.mirth.connect.plugins.datatypes.json.JSONDataTypeProperties" version="3.3.1">
        <batchProperties class="com.mirth.connect.plugins.datatypes.json.JSONBatchProperties" version="3.3.1">
          <batchScript></batchScript>
        </batchProperties>
      </outboundProperties>
    </transformer>
    <filter version="3.3.1">
      <rules/>
    </filter>
    <transportName>HTTP Listener</transportName>
    <mode>SOURCE</mode>
    <enabled>true</enabled>
    <waitForPrevious>true</waitForPrevious>
  </sourceConnector>
  <destinationConnectors>
    <connector version="3.3.1">
      <metaDataId>1</metaDataId>
      <name>Destination 1</name>
      <properties class="com.mirth.connect.connectors.http.HttpDispatcherProperties" version="3.3.1">
        <pluginProperties/>
        <destinationConnectorProperties version="3.3.1">
          <queueEnabled>false</queueEnabled>
          <sendFirst>false</sendFirst>
          <retryIntervalMillis>10000</retryIntervalMillis>
          <regenerateTemplate>false</regenerateTemplate>
          <retryCount>0</retryCount>
          <rotate>false</rotate>
          <includeFilterTransformer>false</includeFilterTransformer>
          <threadCount>1</threadCount>
          <threadAssignmentVariable></threadAssignmentVariable>
          <validateResponse>false</validateResponse>
          <resourceIds class="singleton-set">
            <string>Default Resource</string>
          </resourceIds>
        </destinationConnectorProperties>
        <host>http://localhost:3014/update_order</host>
        <useProxyServer>false</useProxyServer>
        <proxyAddress></proxyAddress>
        <proxyPort></proxyPort>
        <method>post</method>
        <headers class="linked-hash-map"/>
        <parameters class="linked-hash-map"/>
        <responseXmlBody>false</responseXmlBody>
        <responseParseMultipart>true</responseParseMultipart>
        <responseIncludeMetadata>false</responseIncludeMetadata>
        <responseBinaryMimeTypes>application/.*(?&lt;!json|xml)$|image/.*|video/.*|audio/.*</responseBinaryMimeTypes>
        <responseBinaryMimeTypesRegex>true</responseBinaryMimeTypesRegex>
        <multipart>false</multipart>
        <useAuthentication>false</useAuthentication>
        <authenticationType>Basic</authenticationType>
        <usePreemptiveAuthentication>false</usePreemptiveAuthentication>
        <username></username>
        <password></password>
        <content>${message.rawData}</content>
        <contentType>application/json</contentType>
        <dataTypeBinary>false</dataTypeBinary>
        <charset>DEFAULT_ENCODING</charset>
        <socketTimeout>30000</socketTimeout>
      </properties>
      <transformer version="3.3.1">
        <steps/>
        <inboundDataType>JSON</inboundDataType>
        <outboundDataType>JSON</outboundDataType>
        <inboundProperties class="com.mirth.connect.plugins.datatypes.json.JSONDataTypeProperties" version="3.3.1">
          <batchProperties class="com.mirth.connect.plugins.datatypes.json.JSONBatchProperties" version="3.3.1">
            <batchScript></batchScript>
          </batchProperties>
        </inboundProperties>
        <outboundProperties class="com.mirth.connect.plugins.datatypes.json.JSONDataTypeProperties" version="3.3.1">
          <batchProperties class="com.mirth.connect.plugins.datatypes.json.JSONBatchProperties" version="3.3.1">
            <batchScript></batchScript>
          </batchProperties>
        </outboundProperties>
      </transformer>
      <responseTransformer version="3.3.1">
        <steps/>
        <inboundDataType>JSON</inboundDataType>
        <outboundDataType>JSON</outboundDataType>
        <inboundProperties class="com.mirth.connect.plugins.datatypes.json.JSONDataTypeProperties" version="3.3.1">
          <batchProperties class="com.mirth.connect.plugins.datatypes.json.JSONBatchProperties" version="3.3.1">
            <batchScript></batchScript>
          </batchProperties>
        </inboundProperties>
        <outboundProperties class="com.mirth.connect.plugins.datatypes.json.JSONDataTypeProperties" version="3.3.1">
          <batchProperties class="com.mirth.connect.plugins.datatypes.json.JSONBatchProperties" version="3.3.1">
            <batchScript></batchScript>
          </batchProperties>
        </outboundProperties>
      </responseTransformer>
      <filter version="3.3.1">
        <rules/>
      </filter>
      <transportName>HTTP Sender</transportName>
      <mode>DESTINATION</mode>
      <enabled>true</enabled>
      <waitForPrevious>true</waitForPrevious>
    </connector>
  </destinationConnectors>
  <preprocessingScript>// Modify the message variable below to pre process data
return message;</preprocessingScript>
  <postprocessingScript>// This script executes once after a message has been processed
// Responses returned from here will be stored as &quot;Postprocessor&quot; in the response map
return;</postprocessingScript>
  <deployScript>// This script executes once when the channel is deployed
// You only have access to the globalMap and globalChannelMap here to persist data
return;</deployScript>
  <undeployScript>// This script executes once when the channel is undeployed
// You only have access to the globalMap and globalChannelMap here to persist data
return;</undeployScript>
  <properties version="3.3.1">
    <clearGlobalChannelMap>true</clearGlobalChannelMap>
    <messageStorageMode>DEVELOPMENT</messageStorageMode>
    <encryptData>false</encryptData>
    <removeContentOnCompletion>false</removeContentOnCompletion>
    <removeOnlyFilteredOnCompletion>false</removeOnlyFilteredOnCompletion>
    <removeAttachmentsOnCompletion>false</removeAttachmentsOnCompletion>
    <initialState>STARTED</initialState>
    <storeAttachments>false</storeAttachments>
    <tags class="linked-hash-set"/>
    <metaDataColumns>
      <metaDataColumn>
        <name>SOURCE</name>
        <type>STRING</type>
        <mappingName>mirth_source</mappingName>
      </metaDataColumn>
      <metaDataColumn>
        <name>TYPE</name>
        <type>STRING</type>
        <mappingName>mirth_type</mappingName>
      </metaDataColumn>
    </metaDataColumns>
    <attachmentProperties>
      <type>None</type>
      <properties/>
    </attachmentProperties>
    <archiveEnabled>true</archiveEnabled>
    <resourceIds class="linked-hash-set">
      <string>Default Resource</string>
    </resourceIds>
  </properties>
  <codeTemplateLibraries/>
</channel>